geokakao/__init__.py
geokakao/__version__.py
geokakao/geokakao.py
geokakao-0.1.1.dist-info/METADATA
geokakao-0.1.1.dist-info/WHEEL
geokakao-0.1.1.dist-info/top_level.txt
geokakao-0.1.1.dist-info/RECORD
