Metadata-Version: 2.1
Name: geokakao
Version: 0.1.1
Summary: Geospatial Features Using Kakao API
Home-page: https://github.com/osgeokr/geokakao
Author: Byeong-Hyeok Yu
Author-email: bhyu@knps.or.kr
Classifier: Development Status :: 4 - Beta
Classifier: License :: OSI Approved :: GNU General Public License v3 (GPLv3)
Classifier: Programming Language :: Python :: 3.6
Classifier: Programming Language :: Python :: 3.7
Classifier: Programming Language :: Python :: 3.8
Classifier: Programming Language :: Python :: 3.9
Classifier: Programming Language :: Python :: 3.10
Requires-Python: >=3.6
Requires-Dist: requests
Requires-Dist: pandas
Requires-Dist: geopandas
